radarboxplot/__init__.py
radarboxplot/radarboxplot.py
radarboxplot-0.1.3.dist-info/LICENSE
radarboxplot-0.1.3.dist-info/METADATA
radarboxplot-0.1.3.dist-info/WHEEL
radarboxplot-0.1.3.dist-info/top_level.txt
radarboxplot-0.1.3.dist-info/RECORD
