Metadata-Version: 2.1
Name: radarboxplot
Version: 0.1.3
Summary: Implements the radar-boxplot using matplotlib
Home-page: https://github.com/caiohamamura/radarboxplot-python
Author: Caio Hamamura
Author-email: caio.hamamura@usp.br
License: UNKNOWN
Platform: UNKNOWN
Classifier: Programming Language :: Python :: 3
Classifier: License :: OSI Approved :: MIT License
Classifier: Operating System :: OS Independent
Requires-Dist: matplotlib
Requires-Dist: numpy
